setup.py
hamly/__init__.py
hamly/ast_utils.py
hamly/compiler.py
hamly/const.py
hamly/escape.py
hamly/escape_fast.c
hamly/html.py
hamly/loader.py
hamly/optimizer.py
hamly/parser.py
hamly.egg-info/PKG-INFO
hamly.egg-info/SOURCES.txt
hamly.egg-info/dependency_links.txt
hamly.egg-info/not-zip-safe
hamly.egg-info/requires.txt
hamly.egg-info/top_level.txt