Metadata-Version: 1.0
Name: hamly
Version: 0.1
Summary: fast haml for python
Home-page: UNKNOWN
Author: Victor Kotseruba
Author-email: barbuzaster@gmail.com
License: MIT
Keywords: web template haml
Platform: UNKNOWN
